lambdaruntimes/__init__.py
lambda_runtimes-0.0.3.dist-info/LICENSE
lambda_runtimes-0.0.3.dist-info/METADATA
lambda_runtimes-0.0.3.dist-info/WHEEL
lambda_runtimes-0.0.3.dist-info/top_level.txt
lambda_runtimes-0.0.3.dist-info/RECORD
