Metadata-Version: 2.2
Name: lambda-runtimes
Version: 0.0.3
Summary: Scrapes Lambda Runtime Info from Amazon's Docs
Author-email: Ewen McCahon <hi@ewenmccahon.me>
Project-URL: Homepage, https://github.com/Neko-Design/lambda-runtimes
Project-URL: Bug Tracker, https://github.com/Neko-Design/lambda-runtimes/issues
Classifier: Programming Language :: Python :: 3
Classifier: License :: OSI Approved :: MIT License
Classifier: Operating System :: OS Independent
Requires-Python: >=3.7
License-File: LICENSE
Requires-Dist: requests
Requires-Dist: beautifulsoup4
Requires-Dist: python-dateutil
Requires-Dist: pydantic
